django_filter_addons-0.2.0.dist-info/DESCRIPTION.rst
django_filter_addons-0.2.0.dist-info/METADATA
django_filter_addons-0.2.0.dist-info/RECORD
django_filter_addons-0.2.0.dist-info/WHEEL
django_filter_addons-0.2.0.dist-info/metadata.json
django_filter_addons-0.2.0.dist-info/top_level.txt
django_filters_addons/__init__.py
django_filters_addons/filters.py
