Metadata-Version: 2.1
Name: django-filter-addons
Version: 0.2.0
Summary: A collection of addons for django-filter
Home-page: https://github.com/xavierdutreilh/django-filter-addons
Author: Xavier Dutreilh
Author-email: xavier@dutreilh.com
Maintainer: Xavier Dutreilh
Maintainer-email: xavier@dutreilh.com
License: MIT
Platform: UNKNOWN
Classifier: Development Status :: 5 - Production/Stable
Classifier: Environment :: Web Environment
Classifier: Intended Audience :: Developers
Classifier: License :: OSI Approved :: MIT License
Classifier: Operating System :: OS Independent
Classifier: Framework :: Django
Classifier: Framework :: Django :: 1.11
Classifier: Framework :: Django :: 2.0
Classifier: Framework :: Django :: 2.1
Classifier: Framework :: Django :: 2.2
Classifier: Programming Language :: Python
Classifier: Programming Language :: Python :: 3
Classifier: Programming Language :: Python :: 3.5
Classifier: Programming Language :: Python :: 3.6
Classifier: Programming Language :: Python :: 3.7
Requires-Python: >=3.5
